{
  "project_info": {
    "project_number": "502234747976",
    "firebase_url": "https://ongoodterms-default-rtdb.europe-west1.firebasedatabase.app",
    "project_id": "ongoodterms",
    "storage_bucket": "ongoodterms.appspot.com"
  },
  "client": [
    {
      "client_info": {
        "mobilesdk_app_id": "1:502234747976:android:d117be395fc2561262747d",
        "android_client_info": {
          "package_name": "com.example.documentscan"
        }
      },
      "oauth_client": [
        {
          "client_id": "502234747976-ajgs122fpauu1slbvqi2p34eeel9u444.apps.googleusercontent.com",
          "client_type": 1,
          "android_info": {
            "package_name": "com.example.documentscan",
            "certificate_hash": "47fcd940795e2b3fcb3f2cea2906b3d79fa15909"
          }
        },
        {
          "client_id": "502234747976-p94opi939nja8g2it0idri59a5eahk4q.apps.googleusercontent.com",
          "client_type": 3
        }
      ],
      "api_key": [
        {
          "current_key": "AIzaSyDzlgs7tv2awEXUJ1ByPjFcbZHo9e4k5Wg"
        }
      ],
      "services": {
        "appinvite_service": {
          "other_platform_oauth_client": [
            {
              "client_id": "502234747976-p94opi939nja8g2it0idri59a5eahk4q.apps.googleusercontent.com",
              "client_type": 3
            }
          ]
        }
      }
    }
  ],
  "configuration_version": "1"
}